hypothesis_networkx/__init__.py
hypothesis_networkx/strategy.py
hypothesis_networkx-0.3.0.dist-info/LICENSE
hypothesis_networkx-0.3.0.dist-info/METADATA
hypothesis_networkx-0.3.0.dist-info/WHEEL
hypothesis_networkx-0.3.0.dist-info/pbr.json
hypothesis_networkx-0.3.0.dist-info/top_level.txt
hypothesis_networkx-0.3.0.dist-info/RECORD
