Metadata-Version: 2.1
Name: hypothesis_networkx
Version: 0.3.0
Summary: A Hypothesis strategy for generating NetworkX graphs
Home-page: https://github.com/pckroon/hypothesis-networkx
Author: P C Kroon
Author-email: p.c.kroon@rug.nl
License: Apache 2.0
Keywords: hypothesis networkx testing
Classifier: Development Status :: 4 - Beta
Classifier: Intended Audience :: Developers
Classifier: License :: OSI Approved :: Apache Software License
Classifier: Operating System :: OS Independent
Classifier: Programming Language :: Python :: 3
Classifier: Topic :: Software Development :: Libraries :: Python Modules
Classifier: Topic :: Software Development :: Testing
Classifier: Framework :: Hypothesis
License-File: LICENSE
Requires-Dist: pbr
Requires-Dist: networkx
Requires-Dist: hypothesis
